vrft/__init__.py
vrft/control.py
vrft/csvfunc.py
vrft/invfunc.py
pyvrft-1.1.dist-info/LICENSE.txt
pyvrft-1.1.dist-info/METADATA
pyvrft-1.1.dist-info/WHEEL
pyvrft-1.1.dist-info/top_level.txt
pyvrft-1.1.dist-info/RECORD
